div_archive/div32p2.v
`default_nettype none
`timescale 10ps / 1ps

module div32p2
  #( parameter K = 32 )
   ( input wire [K+31:0] x,
     input wire [K-1:0] d,
     output reg [K-1:0] q,
     output reg [K-1:0] r,
     input wire 	clk,
     input wire 	rstn );

integer i;
integer j;
reg [K+31:0] xi[1:0]; // 64
reg [K:0] acc[1:0];   // 33
reg [K-1:0] qi[1:0];  // 32
reg [K-1:0] di[1:0];

always @(posedge clk or negedge rstn) begin
    if (!rstn) begin
        acc[0] <= 0;
        xi[0] <= 0;
        qi[0] <= 0;
        di[0] <= 0;
    end else begin
        acc[0] <= x[63:32];
        xi[0] <= x << 32;
        qi[0] <= 0;
        di[0] <= d;
        for (j = 0; j < 1; j = j + 1) begin
            for (i = 0; i < 16; i = i + 1) begin
                acc[j] = acc[j] << 1 | xi[j][K+31];
                xi[j] = xi[j] << 1;
                qi[j] = qi[j] << 1;
            
                if (acc[j] >= di[j]) begin
                    qi[j] = qi[j] + 1;
                    acc[j] = acc[j] - di[j];
                end
            end
        end
    end
end

always @(posedge clk or negedge rstn) begin
    if (!rstn) begin
        // acc[1] <= 0;
        // xi[1] <= 0;
        // qi[1] <= 0;
        // di[1] <= 0;
    end else begin
        for (j = 0; j < 1; j = j + 1) begin
            for (i = 0; i < 16; i = i + 1) begin
                acc[j] = acc[j] << 1 | xi[j][K+31];
                xi[j] = xi[j] << 1;
                qi[j] = qi[j] << 1;
            
                if (acc[j] >= di[j]) begin
                    qi[j] = qi[j] + 1;
                    acc[j] = acc[j] - di[j];
                end
            end
        end
        r <= acc[0][K-1:0];
        q <= qi[0];
    end
end


endmodule // div32p2

`default_nettype wire

div_archive/test_divider_p2.sv
`timescale 1ns / 1ps
`default_nettype none

module test_divider_p2
  #( parameter K = 32,
     parameter NSTAGE = 2)
   ();
   logic [K+31:0] xi[NSTAGE:0];
   logic [K-1:0]  di[NSTAGE:0];
   logic          val[NSTAGE:0];
   wire [K+31:0]  x;
   wire [K-1:0]   d;
   logic [K-1:0]   r;
   logic [K-1:0]   q;

   logic          clk;
   logic          rstn;
   
   integer        i;
   integer        j;
   logic [K-1:0]  td;
   logic [K-1:0]  th;
   logic [31:0]   tl;

   assign x = xi[0];
   assign d = di[0];
  
   div32p2 udiv32p2(x,d,q,r,clk,rstn);

   initial begin
      $dumpfile("test_divider_p2.vcd");
      $dumpvars(0);

      $display("start of checking module div32p2");

      #1;
      rstn = 0;
      clk = 1;
      val = {default: 1'b0};
      xi[0] = 0;
      di[0] = 0;

      #1;
      clk = 0;
      #1;
      clk = 1;
      rstn = 1;
      
      #1;
      clk = 0;
      #1;
      clk = 1;

      for (i=0;i<100;i++) begin
         td = 0;
         th = 0;
         tl = $urandom();
         /*
          ここはnon blocking代入でなければならない。
          こうすることで、このpositive clock edgeで同時に活性化する
          udiv32p2は、このxiとdiの変化をこの時点で見ずに、
          次のpositive clock edgeで見るようになる。
          */
         xi[0] <= {th,tl};
         di[0] <= td;
         val[0] <= 1;

         #1;
         clk = 0;
         #1;
         clk = 1;
      end

      for (i=0;i<1000;i++) begin
         for (j=1;j<K-7;j++) begin
            td = $urandom()>>j;
            th = (td==0)?('0):($urandom()%td);
            tl = $urandom();
            /*
             ここはnon blocking代入でなければならない。
             こうすることで、このpositive clock edgeで同時に活性化する
             udiv32p2は、このxiとdiの変化をこの時点で見ずに、
             次のpositive clock edgeで見るようになる。
             */
            xi[0] <= {th,tl};
            di[0] <= td;
            val[0] <= 1;

            #1;
            clk = 0;
            #1;
            clk = 1;
         end
      end

      $display("end of checking module div32p2");
      $finish;
   end // initial begin

   always @(posedge clk) begin
      xi[NSTAGE:1] <= xi[NSTAGE-1:0];
      di[NSTAGE:1] <= di[NSTAGE-1:0];
      val[NSTAGE:1] <= val[NSTAGE-1:0];
      if (val[NSTAGE]) begin
         if (di[NSTAGE] != 0) begin
            if (q !== xi[NSTAGE]/di[NSTAGE])
              $display("q %d %d %d %d", xi[NSTAGE],di[NSTAGE],
                       q,xi[NSTAGE]/di[NSTAGE]);
            if (r !== xi[NSTAGE]%di[NSTAGE])
              $display("r %d %d %d %d", xi[NSTAGE],di[NSTAGE],
                       r,xi[NSTAGE]%di[NSTAGE]);
         end else begin
            if (q !== '1)
              $display("q %d %d %d %d", xi[NSTAGE],di[NSTAGE],
                       q,xi[NSTAGE]/di[NSTAGE]);
            if (r !== xi[NSTAGE])
              $display("r %d %d %d %d", xi[NSTAGE],di[NSTAGE],
                       r,xi[NSTAGE]%di[NSTAGE]);
         end
      end
   end
endmodule

`default_nettype wire

div_archive/div32p2check/div32p2check.sim/sim_1/impl/timing/xsim/test_divider_p2.vcd
$date
   Wed Jun  5 20:32:15 2024
$end
$version
  2020.2
$end
$timescale
  1ps
$end
$scope module test_divider_p2 $end
$var wire 64 ! x [63:0] $end
$var wire 32 " d [31:0] $end
$var reg 32 # r [31:0] $end
$var reg 32 $ q [31:0] $end
$var reg 1 % clk $end
$var reg 1 & rstn $end
$var integer 32 ' i $end
$var integer 32 ( j $end
$var reg 32 ) td [31:0] $end
$var reg 32 * th [31:0] $end
$var reg 32 + tl [31:0] $end
$var parameter 32 , K [31:0] $end
$var parameter 32 - NSTAGE [31:0] $end
$scope module udiv32p2 $end
$var wire 64 ! x [63:0] $end
$var wire 32 " d [31:0] $end
$var reg 32 $ q [31:0] $end
$var reg 32 # r [31:0] $end
$var wire 1 . clk $end
$var wire 1 / rstn $end
$var integer 32 0 i $end
$var integer 32 1 j $end
$var parameter 32 2 K [31:0] $end
$upscope $end
$upscope $end
$enddefinitions $end
#0
$dumpvars
bx !
bx "
bx #
bx $
x%
x&
bx '
bx (
bx )
bx *
bx +
b100000 ,
b10 -
x.
x/
bx 0
bx 1
b100000 2
$end
#1000
b0 !
b0 "
1%
0&
1.
0/
#2000
0%
0.
#3000
b0 #
b11111111111111111111111111111111 $
1%
1&
1.
1/
b100000 0
b1 1
#4000
0%
0.
#5000
b1100100110010010011000111011011 !
b0 #
b11111111111111111111111111111111 $
1%
b0 '
b0 )
b0 *
b1100100110010010011000111011011 +
1.
b100000 0
b1 1
#6000
0%
0.
#7000
b1101111101000010010010010111100 !
b0 #
b11111111111111111111111111111111 $
1%
b1 '
b0 )
b0 *
b1101111101000010010010010111100 +
1.
b100000 0
b1 1
#8000
0%
0.
#9000
b1010101001111101111000011111100 !
b1100100110010010011000111011011 #
b11111111111111111111111111111111 $
1%
b10 '
b0 )
b0 *
b1010101001111101111000011111100 +
1.
b100000 0
b1 1
#10000
0%
0.
#11000
b1000110100011001100101010001110 !
b1101111101000010010010010111100 #
b11111111111111111111111111111111 $
1%
b11 '
b0 )
b0 *
b1000110100011001100101010001110 +
1.
b100000 0
b1 1
#12000
0%
0.
#13000
b1101011001111001111010011110000 !
b1010101001111101111000011111100 #
b11111111111111111111111111111111 $
1%
b100 '
b0 )
b0 *
b1101011001111001111010011110000 +
1.
b100000 0
b1 1
#14000
0%
0.
#15000
b1011001000000011001111011011101 !
b1000110100011001100101010001110 #
b11111111111111111111111111111111 $
1%
b101 '
b0 )
b0 *
b1011001000000011001111011011101 +
1.
b100000 0
b1 1
#16000
0%
0.
#17000
b10110100110111111111100011110 !
b1101011001111001111010011110000 #
b11111111111111111111111111111111 $
1%
b110 '
b0 )
b0 *
b10110100110111111111100011110 +
1.
b100000 0
b1 1
#18000
0%
0.
#19000
b1010000000001100010011011001011 !
b1011001000000011001111011011101 #
b11111111111111111111111111111111 $
1%
b111 '
b0 )
b0 *
b1010000000001100010011011001011 +
1.
b100000 0
b1 1
#20000
0%
0.
#21000
b1001000101000101100001110011001 !
b10110100110111111111100011110 #
b11111111111111111111111111111111 $
1%
b1000 '
b0 )
b0 *
b1001000101000101100001110011001 +
1.
b100000 0
b1 1
#22000
0%
0.
#23000
b1101011110110101111000000011011 !
b1010000000001100010011011001011 #
b11111111111111111111111111111111 $
1%
b1001 '
b0 )
b0 *
b1101011110110101111000000011011 +
1.
b100000 0
b1 1
#24000
0%
0.
#25000
b10110100100101111000101011001 !
b1001000101000101100001110011001 #
b11111111111111111111111111111111 $
1%
b1010 '
b0 )
b0 *
b10110100100101111000101011001 +
1.
b100000 0
b1 1
#26000
0%
0.
#27000
b110011110111111011100010001001 !
b1101011110110101111000000011011 #
b11111111111111111111111111111111 $
1%
b1011 '
b0 )
b0 *
b110011110111111011100010001001 +
1.
b100000 0
b1 1
#28000
0%
0.
#29000
b1000100110111001000111011111000 !
b10110100100101111000101011001 #
b11111111111111111111111111111111 $
1%
b1100 '
b0 )
b0 *
b1000100110111001000111011111000 +
1.
b100000 0
b1 1
#30000
0%
0.
#31000
b10101101001011101111000001111000 !
b110011110111111011100010001001 #
b11111111111111111111111111111111 $
1%
b1101 '
b0 )
b0 *
b10101101001011101111000001111000 +
1.
b100000 0
b1 1
#32000
0%
0.
#33000
b11111001011101111101010100 !
b1000100110111001000111011111000 #
b11111111111111111111111111111111 $
1%
b1110 '
b0 )
b0 *
b11111001011101111101010100 +
1.
b100000 0
b1 1
#34000
0%
0.
#35000
b10001101011111110101001010010010 !
b10101101001011101111000001111000 #
b11111111111111111111111111111111 $
1%
b1111 '
b0 )
b0 *
b10001101011111110101001010010010 +
1.
b100000 0
b1 1
#36000
0%
0.
#37000
b10011001000010011110000010010011 !
b11111001011101111101010100 #
b11111111111111111111111111111111 $
1%
b10000 '
b0 )
b0 *
b10011001000010011110000010010011 +
1.
b100000 0
b1 1
#38000
0%
0.
#39000
b10011010011110001101000010101110 !
b10001101011111110101001010010010 #
b11111111111111111111111111111111 $
1%
b10001 '
b0 )
b0 *
b10011010011110001101000010101110 +
1.
b100000 0
b1 1
#40000
0%
0.
#41000
b1000001010111110000101100011011 !
b10011001000010011110000010010011 #
b11111111111111111111111111111111 $
1%
b10010 '
b0 )
b0 *
b1000001010111110000101100011011 +
1.
b100000 0
b1 1
#42000
0%
0.
#43000
b1011101111001100110111110001011 !
b10011010011110001101000010101110 #
b11111111111111111111111111111111 $
1%
b10011 '
b0 )
b0 *
b1011101111001100110111110001011 +
1.
b100000 0
b1 1
#44000
0%
0.
#45000
b1000111101001111100000100100110 !
b1000001010111110000101100011011 #
b11111111111111111111111111111111 $
1%
b10100 '
b0 )
b0 *
b1000111101001111100000100100110 +
1.
b100000 0
b1 1
#46000
0%
0.
#47000
b1000101010001001110101001110000 !
b1011101111001100110111110001011 #
b11111111111111111111111111111111 $
1%
b10101 '
b0 )
b0 *
b1000101010001001110101001110000 +
1.
b100000 0
b1 1
#48000
0%
0.
#49000
b1101011011001011100001000011101 !
b1000111101001111100000100100110 #
b11111111111111111111111111111111 $
1%
b10110 '
b0 )
b0 *
b1101011011001011100001000011101 +
1.
b100000 0
b1 1
#50000
0%
0.
#51000
b1100000101100011010000110111001 !
b1000101010001001110101001110000 #
b11111111111111111111111111111111 $
1%
b10111 '
b0 )
b0 *
b1100000101100011010000110111001 +
1.
b100000 0
b1 1
#52000
0%
0.
#53000
b1011111101111011011101100011110 !
b1101011011001011100001000011101 #
b11111111111111111111111111111111 $
1%
b11000 '
b0 )
b0 *
b1011111101111011011101100011110 +
1.
b100000 0
b1 1
#54000
0%
0.
#55000
b10101100110001001100110100111001 !
b1100000101100011010000110111001 #
b11111111111111111111111111111111 $
1%
b11001 '
b0 )
b0 *
b10101100110001001100110100111001 +
1.
b100000 0
b1 1
#56000
0%
0.
#57000
b111110100110000001000101000100 !
b1011111101111011011101100011110 #
b11111111111111111111111111111111 $
1%
b11010 '
b0 )
b0 *
b111110100110000001000101000100 +
1.
b100000 0
b1 1
#58000
0%
0.
#59000
b10100111011001010111110001000100 !
b10101100110001001100110100111001 #
b11111111111111111111111111111111 $
1%
b11011 '
b0 )
b0 *
b10100111011001010111110001000100 +
1.
b100000 0
b1 1
#60000
0%
0.
#61000
b1110010000010011011011110101001 !
b111110100110000001000101000100 #
b11111111111111111111111111111111 $
1%
b11100 '
b0 )
b0 *
b1110010000010011011011110101001 +
1.
b100000 0
b1 1
#62000
0%
0.
#63000
b10101001111111011101001101100010 !
b10100111011001010111110001000100 #
b11111111111111111111111111111111 $
1%
b11101 '
b0 )
b0 *
b10101001111111011101001101100010 +
1.
b100000 0
b1 1
#64000
0%
0.
#65000
b10001000000101110001110111111101 !
b1110010000010011011011110101001 #
b11111111111111111111111111111111 $
1%
b11110 '
b0 )
b0 *
b10001000000101110001110111111101 +
1.
b100000 0
b1 1
#66000
0%
0.
#67000
b1010001110001110111001011000111 !
b10101001111111011101001101100010 #
b11111111111111111111111111111111 $
1%
b11111 '
b0 )
b0 *
b1010001110001110111001011000111 +
1.
b100000 0
b1 1
#68000
0%
0.
#69000
b1010110110000101010000010011011 !
b10001000000101110001110111111101 #
b11111111111111111111111111111111 $
1%
b100000 '
b0 )
b0 *
b1010110110000101010000010011011 +
1.
b100000 0
b1 1
#70000
0%
0.
#71000
b1000110101011110010111101000001 !
b1010001110001110111001011000111 #
b11111111111111111111111111111111 $
1%
b100001 '
b0 )
b0 *
b1000110101011110010111101000001 +
1.
b100000 0
b1 1
#72000
0%
0.
#73000
b1111001001011001110111100001011 !
b1010110110000101010000010011011 #
b11111111111111111111111111111111 $
1%
b100010 '
b0 )
b0 *
b1111001001011001110111100001011 +
1.
b100000 0
b1 1
#74000
0%
0.
#75000
b1001000110011000101100001000100 !
b1000110101011110010111101000001 #
b11111111111111111111111111111111 $
1%
b100011 '
b0 )
b0 *
b1001000110011000101100001000100 +
1.
b100000 0
b1 1
#76000
0%
0.
#77000
b1110000101011010000001010100011 !
b1111001001011001110111100001011 #
b11111111111111111111111111111111 $
1%
b100100 '
b0 )
b0 *
b1110000101011010000001010100011 +
1.
b100000 0
b1 1
#78000
0%
0.
#79000
b10000001010001000000110100001000 !
b1001000110011000101100001000100 #
b11111111111111111111111111111111 $
1%
b100101 '
b0 )
b0 *
b10000001010001000000110100001000 +
1.
b100000 0
b1 1
#80000
0%
0.
#81000
b10011010100100111100101100001011 !
b1110000101011010000001010100011 #
b11111111111111111111111111111111 $
1%
b100110 '
b0 )
b0 *
b10011010100100111100101100001011 +
1.
b100000 0
b1 1
#82000
0%
0.
#83000
b1000111011011111010001100111110 !
b10000001010001000000110100001000 #
b11111111111111111111111111111111 $
1%
b100111 '
b0 )
b0 *
b1000111011011111010001100111110 +
1.
b100000 0
b1 1
#84000
0%
0.
#85000
b1000111111100110011110001001001 !
b10011010100100111100101100001011 #
b11111111111111111111111111111111 $
1%
b101000 '
b0 )
b0 *
b1000111111100110011110001001001 +
1.
b100000 0
b1 1
#86000
0%
0.
#87000
b10010011110000001011101000010110 !
b1000111011011111010001100111110 #
b11111111111111111111111111111111 $
1%
b101001 '
b0 )
b0 *
b10010011110000001011101000010110 +
1.
b100000 0
b1 1
#88000
0%
0.
#89000
b10000001110111111101110000010 !
b1000111111100110011110001001001 #
b11111111111111111111111111111111 $
1%
b101010 '
b0 )
b0 *
b10000001110111111101110000010 +
1.
b100000 0
b1 1
#90000
0%
0.
#91000
b10111000101000000011111011101101 !
b10010011110000001011101000010110 #
b11111111111111111111111111111111 $
1%
b101011 '
b0 )
b0 *
b10111000101000000011111011101101 +
1.
b100000 0
b1 1
#92000
0%
0.
#93000
b10010101000001001100011100011110 !
b10000001110111111101110000010 #
b11111111111111111111111111111111 $
1%
b101100 '
b0 )
b0 *
b10010101000001001100011100011110 +
1.
b100000 0
b1 1
#94000
0%
0.
#95000
b101010110011111100011010001101 !
b10111000101000000011111011101101 #
b11111111111111111111111111111111 $
1%
b101101 '
b0 )
b0 *
b101010110011111100011010001101 +
1.
b100000 0
b1 1
#96000
0%
0.
#97000
b11111110001000101011 !
b10010101000001001100011100011110 #
b11111111111111111111111111111111 $
1%
b101110 '
b0 )
b0 *
b11111110001000101011 +
1.
b100000 0
b1 1
#98000
0%
0.
#99000
b1011100111110000000001101100111 !
b101010110011111100011010001101 #
b11111111111111111111111111111111 $
1%
b101111 '
b0 )
b0 *
b1011100111110000000001101100111 +
1.
b100000 0
b1 1
#100000
0%
0.
#101000
b111110100100001000000010100011 !
b11111110001000101011 #
b11111111111111111111111111111111 $
1%
b110000 '
b0 )
b0 *
b111110100100001000000010100011 +
1.
b100000 0
b1 1
#102000
0%
0.
#103000
b10010000010010111101110110101110 !
b1011100111110000000001101100111 #
b11111111111111111111111111111111 $
1%
b110001 '
b0 )
b0 *
b10010000010010111101110110101110 +
1.
b100000 0
b1 1
#104000
0%
0.
#105000
b10101100110000100001001010100 !
b111110100100001000000010100011 #
b11111111111111111111111111111111 $
1%
b110010 '
b0 )
b0 *
b10101100110000100001001010100 +
1.
b100000 0
b1 1
#106000
0%
0.
#107000
b1010011100101010100011111000001 !
b10010000010010111101110110101110 #
b11111111111111111111111111111111 $
1%
b110011 '
b0 )
b0 *
b1010011100101010100011111000001 +
1.
b100000 0
b1 1
#108000
0%
0.
#109000
b111011000110111010010000111011 !
b10101100110000100001001010100 #
b11111111111111111111111111111111 $
1%
b110100 '
b0 )
b0 *
b111011000110111010010000111011 +
1.
b100000 0
b1 1
#110000
0%
0.
#111000
b10010101101010000010010010000000 !
b1010011100101010100011111000001 #
b11111111111111111111111111111111 $
1%
b110101 '
b0 )
b0 *
b10010101101010000010010010000000 +
1.
b100000 0
b1 1
#112000
0%
0.
#113000
b10110000100011010100101100101001 !
b111011000110111010010000111011 #
b11111111111111111111111111111111 $
1%
b110110 '
b0 )
b0 *
b10110000100011010100101100101001 +
1.
b100000 0
b1 1
#114000
0%
0.
#115000
b1111001101011000010010011011111 !
b10010101101010000010010010000000 #
b11111111111111111111111111111111 $
1%
b110111 '
b0 )
b0 *
b1111001101011000010010011011111 +
1.
b100000 0
b1 1
#116000
0%
0.
#117000
b10100101111101000000001000101110 !
b10110000100011010100101100101001 #
b11111111111111111111111111111111 $
1%
b111000 '
b0 )
b0 *
b10100101111101000000001000101110 +
1.
b100000 0
b1 1
#118000
0%
0.
#119000
b1000110001001011000110101111101 !
b1111001101011000010010011011111 #
b11111111111111111111111111111111 $
1%
b111001 '
b0 )
b0 *
b1000110001001011000110101111101 +
1.
b100000 0
b1 1
#120000
0%
0.
#121000
b1001101010000010110110010100000 !
b10100101111101000000001000101110 #
b11111111111111111111111111111111 $
1%
b111010 '
b0 )
b0 *
b1001101010000010110110010100000 +
1.
b100000 0
b1 1
#122000
0%
0.
#123000
b1100001000011111010011001101001 !
b1000110001001011000110101111101 #
b11111111111111111111111111111111 $
1%
b111011 '
b0 )
b0 *
b1100001000011111010011001101001 +
1.
b100000 0
b1 1
#124000
0%
0.
#125000
b1011011110011011011000111111101 !
b1001101010000010110110010100000 #
b11111111111111111111111111111111 $
1%
b111100 '
b0 )
b0 *
b1011011110011011011000111111101 +
1.
b100000 0
b1 1
#126000
0%
0.
#127000
b1111101110011101011011111001001 !
b1100001000011111010011001101001 #
b11111111111111111111111111111111 $
1%
b111101 '
b0 )
b0 *
b1111101110011101011011111001001 +
1.
b100000 0
b1 1
#128000
0%
0.
#129000
b1011010101110111100101101001000 !
b1011011110011011011000111111101 #
b11111111111111111111111111111111 $
1%
b111110 '
b0 )
b0 *
b1011010101110111100101101001000 +
1.
b100000 0
b1 1
#130000
0%
0.
#131000
b1110000011011010000101011 !
b1111101110011101011011111001001 #
b11111111111111111111111111111111 $
1%
b111111 '
b0 )
b0 *
b1110000011011010000101011 +
1.
b100000 0
b1 1
#132000
0%
0.
#133000
b1000011111101000100010101000111 !
b1011010101110111100101101001000 #
b11111111111111111111111111111111 $
1%
b1000000 '
b0 )
b0 *
b1000011111101000100010101000111 +
1.
b100000 0
b1 1
#134000
0%
0.
#135000
b10100111111111010011011111101001 !
b1110000011011010000101011 #
b11111111111111111111111111111111 $
1%
b1000001 '
b0 )
b0 *
b10100111111111010011011111101001 +
1.
b100000 0
b1 1
#136000
0%
0.
#137000
b1100010110100010101101010010101 !
b1000011111101000100010101000111 #
b11111111111111111111111111111111 $
1%
b1000010 '
b0 )
b0 *
b1100010110100010101101010010101 +
1.
b100000 0
b1 1
#138000
0%
0.
#139000
b11111110000011111011101000100 !
b10100111111111010011011111101001 #
b11111111111111111111111111111111 $
1%
b1000011 '
b0 )
b0 *
b11111110000011111011101000100 +
1.
b100000 0
b1 1
#140000
0%
0.
#141000
b100101110010111110111110110010 !
b1100010110100010101101010010101 #
b11111111111111111111111111111111 $
1%
b1000100 '
b0 )
b0 *
b100101110010111110111110110010 +
1.
b100000 0
b1 1
#142000
0%
0.
#143000
b111101100011010010010111011101 !
b11111110000011111011101000100 #
b11111111111111111111111111111111 $
1%
b1000101 '
b0 )
b0 *
b111101100011010010010111011101 +
1.
b100000 0
b1 1
#144000
0%
0.
#145000
b10100001100000111010101101110000 !
b100101110010111110111110110010 #
b11111111111111111111111111111111 $
1%
b1000110 '
b0 )
b0 *
b10100001100000111010101101110000 +
1.
b100000 0
b1 1
#146000
0%
0.
#147000
b1101001110000000011010011111001 !
b111101100011010010010111011101 #
b11111111111111111111111111111111 $
1%
b1000111 '
b0 )
b0 *
b1101001110000000011010011111001 +
1.
b100000 0
b1 1
#148000
0%
0.
#149000
b1100101100010100101110111000110 !
b10100001100000111010101101110000 #
b11111111111111111111111111111111 $
1%
b1001000 '
b0 )
b0 *
b1100101100010100101110111000110 +
1.
b100000 0
b1 1
#150000
0%
0.
#151000
b10000100010101010000011000000101 !
b1101001110000000011010011111001 #
b11111111111111111111111111111111 $
1%
b1001001 '
b0 )
b0 *
b10000100010101010000011000000101 +
1.
b100000 0
b1 1
#152000
0%
0.
#153000
b10001001100000100010110000111110 !
b1100101100010100101110111000110 #
b11111111111111111111111111111111 $
1%
b1001010 '
b0 )
b0 *
b10001001100000100010110000111110 +
1.
b100000 0
b1 1
#154000
0%
0.
#155000
b10001011010101100100110101111001 !
b10000100010101010000011000000101 #
b11111111111111111111111111111111 $
1%
b1001011 '
b0 )
b0 *
b10001011010101100100110101111001 +
1.
b100000 0
b1 1
#156000
0%
0.
#157000
b1000001111000100010101111100010 !
b10001001100000100010110000111110 #
b11111111111111111111111111111111 $
1%
b1001100 '
b0 )
b0 *
b1000001111000100010101111100010 +
1.
b100000 0
b1 1
#158000
0%
0.
#159000
b10101011000001011101011110101110 !
b10001011010101100100110101111001 #
b11111111111111111111111111111111 $
1%
b1001101 '
b0 )
b0 *
b10101011000001011101011110101110 +
1.
b100000 0
b1 1
#160000
0%
0.
#161000
b1110101000101101000001001110010 !
b1000001111000100010101111100010 #
b11111111111111111111111111111111 $
1%
b1001110 '
b0 )
b0 *
b1110101000101101000001001110010 +
1.
b100000 0
b1 1
#162000
0%
0.
#163000
b10100111011011001000100110101001 !
b10101011000001011101011110101110 #
b11111111111111111111111111111111 $
1%
b1001111 '
b0 )
b0 *
b10100111011011001000100110101001 +
1.
b100000 0
b1 1
#164000
0%
0.
#165000
b10101111010110101101110110110011 !
b1110101000101101000001001110010 #
b11111111111111111111111111111111 $
1%
b1010000 '
b0 )
b0 *
b10101111010110101101110110110011 +
1.
b100000 0
b1 1
#166000
0%
0.
#167000
b1111110100110001010111010110000 !
b10100111011011001000100110101001 #
b11111111111111111111111111111111 $
1%
b1010001 '
b0 )
b0 *
b1111110100110001010111010110000 +
1.
b100000 0
b1 1
#168000
0%
0.
#169000
b10110010110000101101011100100010 !
b10101111010110101101110110110011 #
b11111111111111111111111111111111 $
1%
b1010010 '
b0 )
b0 *
b10110010110000101101011100100010 +
1.
b100000 0
b1 1
#170000
0%
0.
#171000
b1110001001111010000100110010101 !
b1111110100110001010111010110000 #
b11111111111111111111111111111111 $
1%
b1010011 '
b0 )
b0 *
b1110001001111010000100110010101 +
1.
b100000 0
b1 1
#172000
0%
0.
#173000
b101001100111101000011001011110 !
b10110010110000101101011100100010 #
b11111111111111111111111111111111 $
1%
b1010100 '
b0 )
b0 *
b101001100111101000011001011110 +
1.
b100000 0
b1 1
#174000
0%
0.
#175000
b100111110110010101100110010100 !
b1110001001111010000100110010101 #
b11111111111111111111111111111111 $
1%
b1010101 '
b0 )
b0 *
b100111110110010101100110010100 +
1.
b100000 0
b1 1
#176000
0%
0.
#177000
b11000101010011001001100111110 !
b101001100111101000011001011110 #
b11111111111111111111111111111111 $
1%
b1010110 '
b0 )
b0 *
b11000101010011001001100111110 +
1.
b100000 0
b1 1
#178000
0%
0.
#179000
b1011000111110010110010000010001 !
b100111110110010101100110010100 #
b11111111111111111111111111111111 $
1%
b1010111 '
b0 )
b0 *
b1011000111110010110010000010001 +
1.
b100000 0
b1 1
#180000
0%
0.
#181000
b10100110011100100000100001000101 !
b11000101010011001001100111110 #
b11111111111111111111111111111111 $
1%
b1011000 '
b0 )
b0 *
b10100110011100100000100001000101 +
1.
b100000 0
b1 1
#182000
0%
0.
#183000
b1001011011011000110101001100000 !
b1011000111110010110010000010001 #
b11111111111111111111111111111111 $
1%
b1011001 '
b0 )
b0 *
b1001011011011000110101001100000 +
1.
b100000 0
b1 1
#184000
0%
0.
#185000
b1001010001101100110110110100111 !
b10100110011100100000100001000101 #
b11111111111111111111111111111111 $
1%
b1011010 '
b0 )
b0 *
b1001010001101100110110110100111 +
1.
b100000 0
b1 1
#186000
0%
0.
#187000
b1010000000100001000111010100011 !
b1001011011011000110101001100000 #
b11111111111111111111111111111111 $
1%
b1011011 '
b0 )
b0 *
b1010000000100001000111010100011 +
1.
b100000 0
b1 1
#188000
0%
0.
#189000
b1110011010001011100001111110101 !
b1001010001101100110110110100111 #
b11111111111111111111111111111111 $
1%
b1011100 '
b0 )
b0 *
b1110011010001011100001111110101 +
1.
b100000 0
b1 1
#190000
0%
0.
#191000
b1100010111000000000000011100101 !
b1010000000100001000111010100011 #
b11111111111111111111111111111111 $
1%
b1011101 '
b0 )
b0 *
b1100010111000000000000011100101 +
1.
b100000 0
b1 1
#192000
0%
0.
#193000
b10101001000010011111001010110101 !
b1110011010001011100001111110101 #
b11111111111111111111111111111111 $
1%
b1011110 '
b0 )
b0 *
b10101001000010011111001010110101 +
1.
b100000 0
b1 1
#194000
0%
0.
#195000
b10011001101101111100110000111010 !
b1100010111000000000000011100101 #
b11111111111111111111111111111111 $
1%
b1011111 '
b0 )
b0 *
b10011001101101111100110000111010 +
1.
b100000 0
b1 1
#196000
0%
0.
#197000
b10101110010011000110101101000110 !
b10101001000010011111001010110101 #
b11111111111111111111111111111111 $
1%
b1100000 '
b0 )
b0 *
b10101110010011000110101101000110 +
1.
b100000 0
b1 1
#198000
0%
0.
#199000
b1110011010000000110000001011100 !
b10011001101101111100110000111010 #
b11111111111111111111111111111111 $
1%
b1100001 '
b0 )
b0 *
b1110011010000000110000001011100 +
1.
b100000 0
b1 1
#200000
0%
0.
#201000
b1101001110010000101101011011101 !
b10101110010011000110101101000110 #
b11111111111111111111111111111111 $
1%
b1100010 '
b0 )
b0 *
b1101001110010000101101011011101 +
1.
b100000 0
b1 1
#202000
0%
0.
#203000
b10100001100100100010111100111011 !
b1110011010000000110000001011100 #
b11111111111111111111111111111111 $
1%
b1100011 '
b0 )
b0 *
b10100001100100100010111100111011 +
1.
b100000 0
b1 1
#204000
0%
0.
#205000
b1001011010010010011011001001010111011010010011111101101110101 !
b101011000100000011000010100000 "
b1101001110010000101101011011101 #
b11111111111111111111111111111111 $
1%
b0 '
b1 (
b101011000100000011000010100000 )
b10010110100100100110110010010 *
b10111011010010011111101101110101 +
1.
b100000 0
b1 1
#206000
0%
0.
#207000
b10001010101011100100100100100101000100100101011001010010 !
b1000110110011001100100001 "
b10100001100100100010111100111011 #
b11111111111111111111111111111111 $
1%
b10 (
b1000110110011001100100001 )
b100010101010111001001001 *
b100101000100100101011001010010 +
1.
b100000 0
b1 1
#208000
0%
0.
#209000
b111110101011110010100100010110111111001001010001111100101 !
b100101111111101111101111000 "
b100111011110001110100111010101 #
b1101111111000111001010101101001 $
1%
b11 (
b100101111111101111101111000 )
b1111101010111100101001000 *
b10110111111001001010001111100101 +
1.
b100000 0
b1 1
#210000
0%
0.
#211000
b10101101011011100111111101000111101111101110101000111010011 !
b110000101001000111101110011 "
b11101011011011001010100 #
b1111101010111000111111000111110 $
1%
b100 (
b110000101001000111101110011 )
b101011010110111001111111010 *
b111101111101110101000111010011 +
1.
b100000 0
b1 1
#212000
0%
0.
#213000
b1000011100010011111101000011010001010100110000100000011 !
b100001100101101101001101100 "
b110000101110001101010101 #
b1101001100101011001111100001110 $
1%
b101 (
b100001100101101101001101100 )
b10000111000100111111010 *
b11010001010100110000100000011 +
1.
b100000 0
b1 1
#214000
0%
0.
#215000
b1011010101110101101000011101111010110010100011110010111011 !
b10111110001111111111000101 "
b10001101110011110001111011 #
b11100100001100000000111101001000 $
1%
b110 (
b10111110001111111111000101 )
b10110101011101011010000111 *
b1111010110010100011110010111011 +
1.
b100000 0
b1 1
#216000
0%
0.
#217000
b10011010010100110001010110000001011010010001010000110101 !
b111110000110111010000110 "
b11010101110001000100001111 #
b10000000101011111110101000111 $
1%
b111 (
b111110000110111010000110 )
b100110100101001100010101 *
b10000001011010010001010000110101 +
1.
b100000 0
b1 1
#218000
0%
0.
#219000
b1110100011100101001111001101001010100001110001011100110 !
b100101100110000110100100 "
b1000101000100100110010110 #
b11110100001010111111101111100001 $
1%
b1000 (
b100101100110000110100100 )
b11101000111001010011110 *
b1101001010100001110001011100110 +
1.
b100000 0
b1 1
#220000
0%
0.
#221000
b101110101000001110101010111100100111111111100100010 !
b10010001001010111110000 "
b11011110001001000001 #
b10011111000001101010001001111110 $
1%
b1001 (
b10010001001010111110000 )
b1011101010000011101 *
b1010111100100111111111100100010 +
1.
b100000 0
b1 1
#222000
0%
0.
